kenenet/__init__.py
kenenet-1.3.7.dist-info/METADATA
kenenet-1.3.7.dist-info/WHEEL
kenenet-1.3.7.dist-info/top_level.txt
kenenet-1.3.7.dist-info/RECORD
