Metadata-Version: 2.1
Name: kenenet
Version: 1.3.7
Summary: dude what the fuck even is this package
Home-page: https://www.youtube.com/@KiddyKene
Author: kiddykene
Author-email: kittykingbusiness@gmail.com
Project-URL: Bug Tracker, https://github.com/kiddykene/KeneNet/issues
Classifier: Programming Language :: Python :: 3
Classifier: License :: OSI Approved :: MIT License
Classifier: Operating System :: Microsoft :: Windows
Requires-Python: >=3.6
Requires-Dist: zhmiscellany
Requires-Dist: keyboard
Requires-Dist: mss
Requires-Dist: pyperclip
Requires-Dist: numpy
Requires-Dist: Pillow
Requires-Dist: pydub
Requires-Dist: pygame
Requires-Dist: psutil
Requires-Dist: opencv-python
Requires-Dist: pyautogui
Requires-Dist: pywin32; sys_platform == "win32"
